[{"_id":"6701733e4a3e0cf852558f1a","name":"RELX Pods (Valid QR)","category":"Pods","image":"http://localhost:5002/uploads/1728148286882.jpg","price":180,"branches":{"main":[{"name":"Tobacco","available":true,"_id":"6701733e4a3e0cf852558f1c"},{"name":"Menthol Extra","available":true,"_id":"6701733e4a3e0cf852558f1d"},{"name":"Iced Latte","available":false,"_id":"6701733e4a3e0cf852558f1e"},{"name":"Brown Brew","available":true,"_id":"6701733e4a3e0cf852558f1f"},{"name":"Ice Brew","available":true,"_id":"6701733e4a3e0cf852558f20"},{"name":"Old Town Brew","available":true,"_id":"6701733e4a3e0cf852558f21"},{"name":"Hazelnut Latte","available":false,"_id":"6701733e4a3e0cf852558f22"},{"name":"Purple Snow","available":true,"_id":"6701733e4a3e0cf852558f23"},{"name":"Fragrant Burst","available":false,"_id":"6701733e4a3e0cf852558f24"},{"name":"Gardens Heart","available":true,"_id":"6701733e4a3e0cf852558f25"},{"name":"Fresh Red","available":true,"_id":"6701733e4a3e0cf852558f26"},{"name":"Tangy Gems","available":false,"_id":"6701733e4a3e0cf852558f27"},{"name":"Red Swirls","available":true,"_id":"6701733e4a3e0cf852558f28"},{"name":"White Freeze","available":true,"_id":"6701733e4a3e0cf852558f29"},{"name":"Ginger Tea","available":false,"_id":"6701733e4a3e0cf852558f2a"},{"name":"Classic Tobacco","available":true,"_id":"6701733e4a3e0cf852558f2b"},{"name":"Tangy Purple","available":true,"_id":"6701733e4a3e0cf852558f2c"},{"name":"Dark Sparkle","available":true,"_id":"6701733e4a3e0cf852558f2d"},{"name":"Crisp Green","available":true,"_id":"6701733e4a3e0cf852558f2e"}],"second":[{"name":"Tobacco","available":true,"_id":"6701733e4a3e0cf852558f2f"},{"name":"Menthol Extra","available":true,"_id":"6701733e4a3e0cf852558f30"},{"name":"Iced Latte","available":true,"_id":"6701733e4a3e0cf852558f31"},{"name":"Brown Brew","available":true,"_id":"6701733e4a3e0cf852558f32"},{"name":"Ice Brew","available":false,"_id":"6701733e4a3e0cf852558f33"},{"name":"Old Town Brew","available":false,"_id":"6701733e4a3e0cf852558f34"},{"name":"Hazelnut Latte","available":true,"_id":"6701733e4a3e0cf852558f35"},{"name":"Purple Snow","available":true,"_id":"6701733e4a3e0cf852558f36"},{"name":"Fragrant Burst","available":false,"_id":"6701733e4a3e0cf852558f37"},{"name":"Gardens Heart","available":true,"_id":"6701733e4a3e0cf852558f38"},{"name":"Fresh Red","available":true,"_id":"6701733e4a3e0cf852558f39"},{"name":"Tangy Gems","available":true,"_id":"6701733e4a3e0cf852558f3a"},{"name":"Red Swirls","available":true,"_id":"6701733e4a3e0cf852558f3b"},{"name":"White Freeze","available":true,"_id":"6701733e4a3e0cf852558f3c"},{"name":"Ginger Tea","available":true,"_id":"6701733e4a3e0cf852558f3d"},{"name":"Classic Tobacco","available":true,"_id":"6701733e4a3e0cf852558f3e"},{"name":"Tangy Purple","available":true,"_id":"6701733e4a3e0cf852558f3f"},{"name":"Dark Sparkle","available":true,"_id":"6701733e4a3e0cf852558f40"},{"name":"Crisp Green","available":true,"_id":"6701733e4a3e0cf852558f41"}],"third":[{"name":"Tobacco","available":true,"_id":"6701733e4a3e0cf852558f42"},{"name":"Menthol Extra","available":false,"_id":"6701733e4a3e0cf852558f43"},{"name":"Iced Latte","available":false,"_id":"6701733e4a3e0cf852558f44"},{"name":"Brown Brew","available":true,"_id":"6701733e4a3e0cf852558f45"},{"name":"Ice Brew","available":false,"_id":"6701733e4a3e0cf852558f46"},{"name":"Old Town Brew","available":false,"_id":"6701733e4a3e0cf852558f47"},{"name":"Hazelnut Latte","available":false,"_id":"6701733e4a3e0cf852558f48"},{"name":"Purple Snow","available":true,"_id":"6701733e4a3e0cf852558f49"},{"name":"Fragrant Burst","available":false,"_id":"6701733e4a3e0cf852558f4a"},{"name":"Gardens Heart","available":true,"_id":"6701733e4a3e0cf852558f4b"},{"name":"Fresh Red","available":true,"_id":"6701733e4a3e0cf852558f4c"},{"name":"Tangy Gems","available":false,"_id":"6701733e4a3e0cf852558f4d"},{"name":"Red Swirls","available":true,"_id":"6701733e4a3e0cf852558f4e"},{"name":"White Freeze","available":true,"_id":"6701733e4a3e0cf852558f4f"},{"name":"Ginger Tea","available":false,"_id":"6701733e4a3e0cf852558f50"},{"name":"Classic Tobacco","available":true,"_id":"6701733e4a3e0cf852558f51"},{"name":"Tangy Purple","available":true,"_id":"6701733e4a3e0cf852558f52"},{"name":"Dark Sparkle","available":true,"_id":"6701733e4a3e0cf852558f53"},{"name":"Crisp Green","available":true,"_id":"6701733e4a3e0cf852558f54"}],"_id":"6701733e4a3e0cf852558f1b"},"__v":0},{"_id":"670173f14a3e0cf85255903e","name":"BOSS Pods","category":"Pods","image":"http://localhost:5002/uploads/1728148465293.jpg","price":130,"branches":{"main":[{"name":"Very Black - Black Currant","available":true,"_id":"670173f14a3e0cf852559040"},{"name":"Royal Purple - Grapes","available":true,"_id":"670173f14a3e0cf852559041"},{"name":"Very Mixed - Mixed Berries\t","available":true,"_id":"670173f14a3e0cf852559042"},{"name":"Lush Ice - Watermelon","available":true,"_id":"670173f14a3e0cf852559043"},{"name":"Fresh Mint - Menthol","available":true,"_id":"670173f14a3e0cf852559044"},{"name":"White In Red - Lychee","available":true,"_id":"670173f14a3e0cf852559045"},{"name":"Wild Pink - Strawberry Ice","available":true,"_id":"670173f14a3e0cf852559046"},{"name":"Pink Freeze - Strawberry Ice Cream","available":true,"_id":"670173f14a3e0cf852559047"}],"second":[{"name":"Very Black - Black Currant","available":true,"_id":"670173f14a3e0cf852559048"},{"name":"Royal Purple - Grapes","available":true,"_id":"670173f14a3e0cf852559049"},{"name":"Very Mixed - Mixed Berries\t","available":true,"_id":"670173f14a3e0cf85255904a"},{"name":"Lush Ice - Watermelon","available":true,"_id":"670173f14a3e0cf85255904b"},{"name":"Fresh Mint - Menthol","available":true,"_id":"670173f14a3e0cf85255904c"},{"name":"White In Red - Lychee","available":true,"_id":"670173f14a3e0cf85255904d"},{"name":"Wild Pink - Strawberry Ice","available":true,"_id":"670173f14a3e0cf85255904e"},{"name":"Pink Freeze - Strawberry Ice Cream","available":true,"_id":"670173f14a3e0cf85255904f"}],"third":[{"name":"Very Black - Black Currant","available":true,"_id":"670173f14a3e0cf852559050"},{"name":"Royal Purple - Grapes","available":true,"_id":"670173f14a3e0cf852559051"},{"name":"Very Mixed - Mixed Berries\t","available":true,"_id":"670173f14a3e0cf852559052"},{"name":"Lush Ice - Watermelon","available":true,"_id":"670173f14a3e0cf852559053"},{"name":"Fresh Mint - Menthol","available":true,"_id":"670173f14a3e0cf852559054"},{"name":"White In Red - Lychee","available":true,"_id":"670173f14a3e0cf852559055"},{"name":"Wild Pink - Strawberry Ice","available":true,"_id":"670173f14a3e0cf852559056"},{"name":"Pink Freeze - Strawberry Ice Cream","available":true,"_id":"670173f14a3e0cf852559057"}],"_id":"670173f14a3e0cf85255903f"},"__v":0},{"_id":"6701744d4a3e0cf8525591a1","name":"Ryuu Pods","category":"Pods","image":"http://localhost:5002/uploads/1728148557360.jpg","price":350,"branches":{"main":[{"name":"Bubble Blower - Bubblegum","available":true,"_id":"6701744d4a3e0cf8525591a3"},{"name":"Green Tokyo - Matcha","available":true,"_id":"6701744d4a3e0cf8525591a4"},{"name":"Red Pulp - Watermelon Ice","available":true,"_id":"6701744d4a3e0cf8525591a5"},{"name":"Very More - Mix Berries","available":true,"_id":"6701744d4a3e0cf8525591a6"},{"name":"Trouble Purple - Grapes Ice","available":true,"_id":"6701744d4a3e0cf8525591a7"},{"name":"Verry Baguio - Strawberry Ice","available":true,"_id":"6701744d4a3e0cf8525591a8"},{"name":"Blue Freeze - Blueberry Ice","available":true,"_id":"6701744d4a3e0cf8525591a9"},{"name":"Cheerblast - Lychee Ice","available":true,"_id":"6701744d4a3e0cf8525591aa"}],"second":[{"name":"Bubble Blower - Bubblegum","available":true,"_id":"6701744d4a3e0cf8525591ab"},{"name":"Green Tokyo - Matcha","available":true,"_id":"6701744d4a3e0cf8525591ac"},{"name":"Red Pulp - Watermelon Ice","available":true,"_id":"6701744d4a3e0cf8525591ad"},{"name":"Very More - Mix Berries","available":true,"_id":"6701744d4a3e0cf8525591ae"},{"name":"Trouble Purple - Grapes Ice","available":true,"_id":"6701744d4a3e0cf8525591af"},{"name":"Verry Baguio - Strawberry Ice","available":false,"_id":"6701744d4a3e0cf8525591b0"},{"name":"Blue Freeze - Blueberry Ice","available":true,"_id":"6701744d4a3e0cf8525591b1"},{"name":"Cheerblast - Lychee Ice","available":true,"_id":"6701744d4a3e0cf8525591b2"},{"name":"","available":true,"_id":"6701747c4a3e0cf8525593a8"}],"third":[{"name":"Bubble Blower - Bubblegum","available":true,"_id":"6701744d4a3e0cf8525591b3"},{"name":"Green Tokyo - Matcha","available":true,"_id":"6701744d4a3e0cf8525591b4"},{"name":"Red Pulp - Watermelon Ice","available":true,"_id":"6701744d4a3e0cf8525591b5"},{"name":"Very More - Mix Berries","available":true,"_id":"6701744d4a3e0cf8525591b6"},{"name":"Trouble Purple - Grapes Ice","available":true,"_id":"6701744d4a3e0cf8525591b7"},{"name":"Verry Baguio - Strawberry Ice","available":false,"_id":"6701744d4a3e0cf8525591b8"},{"name":"Blue Freeze - Blueberry Ice","available":true,"_id":"6701744d4a3e0cf8525591b9"},{"name":"Cheerblast - Lychee Ice","available":true,"_id":"6701744d4a3e0cf8525591ba"},{"name":"","available":true,"_id":"6701747c4a3e0cf8525593b1"}],"_id":"6701744d4a3e0cf8525591a2"},"__v":0},{"_id":"670174e04a3e0cf8525594a8","name":"SHIFT Chillax Go X 2.0 Pods","category":"Pods","image":"http://localhost:5002/uploads/1728148704297.jpg","price":300,"branches":{"main":[{"name":"Ube Jam","available":false,"_id":"670174e04a3e0cf8525594aa"},{"name":"Cola Ice","available":false,"_id":"670174e04a3e0cf8525594ab"},{"name":"Strawberry Ice","available":false,"_id":"670174e04a3e0cf8525594ac"},{"name":"Mint Ice","available":false,"_id":"670174e04a3e0cf8525594ad"},{"name":"Grape Bubblegum","available":false,"_id":"670174e04a3e0cf8525594ae"},{"name":"Old Tobacco","available":true,"_id":"670174e04a3e0cf8525594af"},{"name":"Blueberry Pancake","available":false,"_id":"670174e04a3e0cf8525594b0"},{"name":"Mix Berries","available":false,"_id":"670174e04a3e0cf8525594b1"},{"name":"Yakult Ice","available":false,"_id":"670174e04a3e0cf8525594b2"},{"name":"Ice Lychee","available":false,"_id":"670174e04a3e0cf8525594b3"},{"name":"Ice Bubblegum","available":false,"_id":"670174e04a3e0cf8525594b4"},{"name":"Watermelon Ice","available":false,"_id":"670174e04a3e0cf8525594b5"},{"name":"Avocado","available":false,"_id":"670174e04a3e0cf8525594b6"},{"name":"Sweet Honeydew","available":false,"_id":"670174e04a3e0cf8525594b7"},{"name":"Blackcurrant","available":false,"_id":"670174e04a3e0cf8525594b8"}],"second":[{"name":"Ube Jam","available":true,"_id":"670174e04a3e0cf8525594b9"},{"name":"Cola Ice","available":true,"_id":"670174e04a3e0cf8525594ba"},{"name":"Strawberry Ice","available":false,"_id":"670174e04a3e0cf8525594bb"},{"name":"Mint Ice","available":false,"_id":"670174e04a3e0cf8525594bc"},{"name":"Grape Bubblegum","available":false,"_id":"670174e04a3e0cf8525594bd"},{"name":"Old Tobacco","available":true,"_id":"670174e04a3e0cf8525594be"},{"name":"Blueberry Pancake","available":true,"_id":"670174e04a3e0cf8525594bf"},{"name":"Mix Berries","available":false,"_id":"670174e04a3e0cf8525594c0"},{"name":"Yakult Ice","available":false,"_id":"670174e04a3e0cf8525594c1"},{"name":"Ice Lychee","available":false,"_id":"670174e04a3e0cf8525594c2"},{"name":"Ice Bubblegum","available":false,"_id":"670174e04a3e0cf8525594c3"},{"name":"Watermelon Ice","available":false,"_id":"670174e04a3e0cf8525594c4"},{"name":"Avocado","available":true,"_id":"670174e04a3e0cf8525594c5"},{"name":"Sweet Honeydew","available":false,"_id":"670174e04a3e0cf8525594c6"},{"name":"Blackcurrant","available":false,"_id":"670174e04a3e0cf8525594c7"},{"name":"","available":true,"_id":"670176354a3e0cf852559ff3"}],"third":[{"name":"Ube Jam","available":true,"_id":"670174e04a3e0cf8525594c8"},{"name":"Cola Ice","available":true,"_id":"670174e04a3e0cf8525594c9"},{"name":"Strawberry Ice","available":false,"_id":"670174e04a3e0cf8525594ca"},{"name":"Mint Ice","available":true,"_id":"670174e04a3e0cf8525594cb"},{"name":"Grape Bubblegum","available":false,"_id":"670174e04a3e0cf8525594cc"},{"name":"Old Tobacco","available":true,"_id":"670174e04a3e0cf8525594cd"},{"name":"Blueberry Pancake","available":true,"_id":"670174e04a3e0cf8525594ce"},{"name":"Mix Berries","available":false,"_id":"670174e04a3e0cf8525594cf"},{"name":"Yakult Ice","available":true,"_id":"670174e04a3e0cf8525594d0"},{"name":"Ice Lychee","available":false,"_id":"670174e04a3e0cf8525594d1"},{"name":"Ice Bubblegum","available":false,"_id":"670174e04a3e0cf8525594d2"},{"name":"Watermelon Ice","available":false,"_id":"670174e04a3e0cf8525594d3"},{"name":"Avocado","available":true,"_id":"670174e04a3e0cf8525594d4"},{"name":"Sweet Honeydew","available":false,"_id":"670174e04a3e0cf8525594d5"},{"name":"Blackcurrant","available":false,"_id":"670174e04a3e0cf8525594d6"},{"name":"","available":true,"_id":"670176354a3e0cf85255a003"}],"_id":"670174e04a3e0cf8525594a9"},"__v":0},{"_id":"670176174a3e0cf85255960c","name":"VAPENGIN Jupiter Pods","category":"Pods","image":"http://localhost:5002/uploads/1728149015210.jpg","price":250,"branches":{"main":[{"name":"Golden Green Sphere - Avocado","available":true,"_id":"670176174a3e0cf85255960e"},{"name":"Red Snow - Strawberry Icecream","available":true,"_id":"670176174a3e0cf85255960f"},{"name":"Brown RY4 - Caramel Tobacco","available":true,"_id":"670176174a3e0cf852559610"},{"name":"Rainbow Bubble - Bubblegum","available":true,"_id":"670176174a3e0cf852559611"},{"name":"Red Green Wishes - Strawberry Kiwi","available":true,"_id":"670176174a3e0cf852559612"},{"name":"Blue Snowy Blends - Blueberry Ice","available":true,"_id":"670176174a3e0cf852559613"},{"name":"Double Dancer - Double Apple","available":true,"_id":"670176174a3e0cf852559614"},{"name":"Purple Snow - Taro Icecream","available":true,"_id":"670176174a3e0cf852559615"},{"name":"Sunrise Orchard - Watermelon Lychee","available":true,"_id":"670176174a3e0cf852559616"},{"name":"Sunny Snowy Fun - Ice Watermelon","available":true,"_id":"670176174a3e0cf852559617"},{"name":"Smooth Current - Aloe Blackcurrant","available":true,"_id":"670176174a3e0cf852559618"},{"name":"Orchard Blends - Mixed Berries","available":true,"_id":"670176174a3e0cf852559619"},{"name":"Snowy Cluster - Grape Ice","available":true,"_id":"670176174a3e0cf85255961a"},{"name":"Red Sunrise - Strawberry Ice Cream","available":true,"_id":"670176174a3e0cf85255961b"}],"second":[{"name":"Golden Green Sphere - Avocado","available":true,"_id":"670176174a3e0cf85255961c"},{"name":"Red Snow - Strawberry Icecream","available":true,"_id":"670176174a3e0cf85255961d"},{"name":"Brown RY4 - Caramel Tobacco","available":true,"_id":"670176174a3e0cf85255961e"},{"name":"Rainbow Bubble - Bubblegum","available":true,"_id":"670176174a3e0cf85255961f"},{"name":"Red Green Wishes - Strawberry Kiwi","available":true,"_id":"670176174a3e0cf852559620"},{"name":"Blue Snowy Blends - Blueberry Ice","available":true,"_id":"670176174a3e0cf852559621"},{"name":"Double Dancer - Double Apple","available":true,"_id":"670176174a3e0cf852559622"},{"name":"Purple Snow - Taro Icecream","available":true,"_id":"670176174a3e0cf852559623"},{"name":"Sunrise Orchard - Watermelon Lychee","available":true,"_id":"670176174a3e0cf852559624"},{"name":"Sunny Snowy Fun - Ice Watermelon","available":true,"_id":"670176174a3e0cf852559625"},{"name":"Smooth Current - Aloe Blackcurrant","available":true,"_id":"670176174a3e0cf852559626"},{"name":"Orchard Blends - Mixed Berries","available":true,"_id":"670176174a3e0cf852559627"},{"name":"Snowy Cluster - Grape Ice","available":true,"_id":"670176174a3e0cf852559628"},{"name":"Red Sunrise - Strawberry Ice Cream","available":true,"_id":"670176174a3e0cf852559629"},{"name":"","available":true,"_id":"670176414a3e0cf85255a237"}],"third":[{"name":"Golden Green Sphere - Avocado","available":true,"_id":"670176174a3e0cf85255962a"},{"name":"Red Snow - Strawberry Icecream","available":true,"_id":"670176174a3e0cf85255962b"},{"name":"Brown RY4 - Caramel Tobacco","available":true,"_id":"670176174a3e0cf85255962c"},{"name":"Rainbow Bubble - Bubblegum","available":true,"_id":"670176174a3e0cf85255962d"},{"name":"Red Green Wishes - Strawberry Kiwi","available":true,"_id":"670176174a3e0cf85255962e"},{"name":"Blue Snowy Blends - Blueberry Ice","available":true,"_id":"670176174a3e0cf85255962f"},{"name":"Double Dancer - Double Apple","available":true,"_id":"670176174a3e0cf852559630"},{"name":"Purple Snow - Taro Icecream","available":true,"_id":"670176174a3e0cf852559631"},{"name":"Sunrise Orchard - Watermelon Lychee","available":true,"_id":"670176174a3e0cf852559632"},{"name":"Sunny Snowy Fun - Ice Watermelon","available":true,"_id":"670176174a3e0cf852559633"},{"name":"Smooth Current - Aloe Blackcurrant","available":true,"_id":"670176174a3e0cf852559634"},{"name":"Orchard Blends - Mixed Berries","available":true,"_id":"670176174a3e0cf852559635"},{"name":"Snowy Cluster - Grape Ice","available":true,"_id":"670176174a3e0cf852559636"},{"name":"Red Sunrise - Strawberry Ice Cream","available":true,"_id":"670176174a3e0cf852559637"},{"name":"","available":true,"_id":"670176414a3e0cf85255a246"}],"_id":"670176174a3e0cf85255960d"},"__v":0},{"_id":"670177ec4a3e0cf85255c2d7","name":"Ryuu Device (Battery)","category":"Devices","image":"http://localhost:5002/uploads/1728149484323.jpg","price":350,"branches":{"main":[{"name":"Battery","available":true,"_id":"670177ec4a3e0cf85255c2d9"}],"second":[{"name":"Battery","available":true,"_id":"670177ec4a3e0cf85255c2da"}],"third":[{"name":"Battery","available":true,"_id":"670177ec4a3e0cf85255c2db"}],"_id":"670177ec4a3e0cf85255c2d8"},"__v":0},{"_id":"670178064a3e0cf85255c471","name":"SHIFT Chillax Go X 2.0 Device (Battery)\t","category":"Devices","image":"http://localhost:5002/uploads/1728149510269.jpg","price":200,"branches":{"main":[{"name":"Battery","available":true,"_id":"670178064a3e0cf85255c473"}],"second":[{"name":"Battery","available":true,"_id":"670178064a3e0cf85255c474"}],"third":[{"name":"Battery","available":true,"_id":"670178064a3e0cf85255c475"}],"_id":"670178064a3e0cf85255c472"},"__v":0},{"_id":"6701783b4a3e0cf85255c7bb","name":"VAPENGIN Jupiter Device (Battery)","category":"Devices","image":"http://localhost:5002/uploads/1728149563169.jpg","price":200,"branches":{"main":[{"name":"Battery","available":true,"_id":"6701783b4a3e0cf85255c7bd"}],"second":[{"name":"Battery","available":true,"_id":"6701783b4a3e0cf85255c7be"}],"third":[{"name":"Battery","available":true,"_id":"6701783b4a3e0cf85255c7bf"}],"_id":"6701783b4a3e0cf85255c7bc"},"__v":0},{"_id":"6701792f4a3e0cf85255c9ad","name":"BLACK Elite V1 (8000 Puffs) Pods","category":"Pods","image":"http://localhost:5002/uploads/1728149807647.jpg","price":300,"branches":{"main":[{"name":"Very Baguio - Strawberry","available":true,"_id":"6701792f4a3e0cf85255c9af"},{"name":"Red Cannon - Bubblegum","available":true,"_id":"6701792f4a3e0cf85255c9b0"},{"name":"Cheer Blast - Lychee","available":true,"_id":"6701792f4a3e0cf85255c9b1"},{"name":"Very More - Mixed Berries","available":true,"_id":"6701792f4a3e0cf85255c9b2"},{"name":"Black Wave - Black Currant","available":true,"_id":"6701792f4a3e0cf85255c9b3"},{"name":"Pitch Perfect - Honey Peach","available":false,"_id":"6701792f4a3e0cf85255c9b4"},{"name":"Sparkle Squeeze - Lemon Cola ","available":true,"_id":"6701792f4a3e0cf85255c9b5"},{"name":"Blue Freeze - Blueberry Ice","available":true,"_id":"6701792f4a3e0cf85255c9b6"},{"name":"Red Pulp - Watermelon","available":true,"_id":"6701792f4a3e0cf85255c9b7"},{"name":"Trouble Purple - Grapes","available":true,"_id":"6701792f4a3e0cf85255c9b8"},{"name":"Bacteria Monster - Yakult","available":true,"_id":"6701792f4a3e0cf85255c9b9"},{"name":"Green Tokyo - Matcha","available":true,"_id":"6701792f4a3e0cf85255c9ba"}],"second":[{"name":"Very Baguio - Strawberry","available":true,"_id":"6701792f4a3e0cf85255c9bb"},{"name":"Red Cannon - Bubblegum","available":true,"_id":"6701792f4a3e0cf85255c9bc"},{"name":"Cheer Blast - Lychee","available":true,"_id":"6701792f4a3e0cf85255c9bd"},{"name":"Very More - Mixed Berries","available":true,"_id":"6701792f4a3e0cf85255c9be"},{"name":"Black Wave - Black Currant","available":true,"_id":"6701792f4a3e0cf85255c9bf"},{"name":"Pitch Perfect - Honey Peach","available":false,"_id":"6701792f4a3e0cf85255c9c0"},{"name":"Sparkle Squeeze - Lemon Cola ","available":true,"_id":"6701792f4a3e0cf85255c9c1"},{"name":"Blue Freeze - Blueberry Ice","available":true,"_id":"6701792f4a3e0cf85255c9c2"},{"name":"Red Pulp - Watermelon","available":true,"_id":"6701792f4a3e0cf85255c9c3"},{"name":"Trouble Purple - Grapes","available":true,"_id":"6701792f4a3e0cf85255c9c4"},{"name":"Bacteria Monster - Yakult","available":true,"_id":"6701792f4a3e0cf85255c9c5"},{"name":"Green Tokyo - Matcha","available":true,"_id":"6701792f4a3e0cf85255c9c6"}],"third":[{"name":"Very Baguio - Strawberry","available":true,"_id":"6701792f4a3e0cf85255c9c7"},{"name":"Red Cannon - Bubblegum","available":true,"_id":"6701792f4a3e0cf85255c9c8"},{"name":"Cheer Blast - Lychee","available":true,"_id":"6701792f4a3e0cf85255c9c9"},{"name":"Very More - Mixed Berries","available":true,"_id":"6701792f4a3e0cf85255c9ca"},{"name":"Black Wave - Black Currant","available":true,"_id":"6701792f4a3e0cf85255c9cb"},{"name":"Pitch Perfect - Honey Peach","available":false,"_id":"6701792f4a3e0cf85255c9cc"},{"name":"Sparkle Squeeze - Lemon Cola ","available":true,"_id":"6701792f4a3e0cf85255c9cd"},{"name":"Blue Freeze - Blueberry Ice","available":true,"_id":"6701792f4a3e0cf85255c9ce"},{"name":"Red Pulp - Watermelon","available":true,"_id":"6701792f4a3e0cf85255c9cf"},{"name":"Trouble Purple - Grapes","available":true,"_id":"6701792f4a3e0cf85255c9d0"},{"name":"Bacteria Monster - Yakult","available":true,"_id":"6701792f4a3e0cf85255c9d1"},{"name":"Green Tokyo - Matcha","available":true,"_id":"6701792f4a3e0cf85255c9d2"}],"_id":"6701792f4a3e0cf85255c9ae"},"__v":0},{"_id":"670179804a3e0cf85255cda4","name":"BLACK Elite V2 (12000 Puffs) Pods","category":"Pods","image":"http://localhost:5002/uploads/1728149888523.jpg","price":350,"branches":{"main":[{"name":"Rainbow Punch - Kool Aid","available":true,"_id":"670179804a3e0cf85255cda6"},{"name":"Green Tokyo - Matcha","available":true,"_id":"670179804a3e0cf85255cda7"},{"name":"Yellow Summer - Mango","available":true,"_id":"670179804a3e0cf85255cda8"},{"name":"Yellow Green - Lemon Lime","available":true,"_id":"670179804a3e0cf85255cda9"},{"name":"Sweet Forest - Green Apple","available":true,"_id":"670179804a3e0cf85255cdaa"},{"name":"Very More - Mix Berries","available":true,"_id":"670179804a3e0cf85255cdab"},{"name":"Trouble Purple - Grapes Ice","available":true,"_id":"670179804a3e0cf85255cdac"},{"name":"Black Wave - Blackcurrant","available":true,"_id":"670179804a3e0cf85255cdad"},{"name":"Red Pulp - Watermelon Ice","available":true,"_id":"670179804a3e0cf85255cdae"},{"name":"Very Baguio - Strawberry Ice","available":true,"_id":"670179804a3e0cf85255cdaf"},{"name":"Bacteria Monster - Yakult","available":true,"_id":"670179804a3e0cf85255cdb0"}],"second":[{"name":"Rainbow Punch - Kool Aid","available":true,"_id":"670179804a3e0cf85255cdb1"},{"name":"Green Tokyo - Matcha","available":true,"_id":"670179804a3e0cf85255cdb2"},{"name":"Yellow Summer - Mango","available":true,"_id":"670179804a3e0cf85255cdb3"},{"name":"Yellow Green - Lemon Lime","available":true,"_id":"670179804a3e0cf85255cdb4"},{"name":"Sweet Forest - Green Apple","available":true,"_id":"670179804a3e0cf85255cdb5"},{"name":"Very More - Mix Berries","available":true,"_id":"670179804a3e0cf85255cdb6"},{"name":"Trouble Purple - Grapes Ice","available":true,"_id":"670179804a3e0cf85255cdb7"},{"name":"Black Wave - Blackcurrant","available":true,"_id":"670179804a3e0cf85255cdb8"},{"name":"Red Pulp - Watermelon Ice","available":true,"_id":"670179804a3e0cf85255cdb9"},{"name":"Very Baguio - Strawberry Ice","available":true,"_id":"670179804a3e0cf85255cdba"},{"name":"Bacteria Monster - Yakult","available":true,"_id":"670179804a3e0cf85255cdbb"}],"third":[{"name":"Rainbow Punch - Kool Aid","available":true,"_id":"670179804a3e0cf85255cdbc"},{"name":"Green Tokyo - Matcha","available":true,"_id":"670179804a3e0cf85255cdbd"},{"name":"Yellow Summer - Mango","available":true,"_id":"670179804a3e0cf85255cdbe"},{"name":"Yellow Green - Lemon Lime","available":true,"_id":"670179804a3e0cf85255cdbf"},{"name":"Sweet Forest - Green Apple","available":true,"_id":"670179804a3e0cf85255cdc0"},{"name":"Very More - Mix Berries","available":true,"_id":"670179804a3e0cf85255cdc1"},{"name":"Trouble Purple - Grapes Ice","available":true,"_id":"670179804a3e0cf85255cdc2"},{"name":"Black Wave - Blackcurrant","available":true,"_id":"670179804a3e0cf85255cdc3"},{"name":"Red Pulp - Watermelon Ice","available":true,"_id":"670179804a3e0cf85255cdc4"},{"name":"Very Baguio - Strawberry Ice","available":true,"_id":"670179804a3e0cf85255cdc5"},{"name":"Bacteria Monster - Yakult","available":true,"_id":"670179804a3e0cf85255cdc6"}],"_id":"670179804a3e0cf85255cda5"},"__v":0},{"_id":"670179b84a3e0cf85255d21c","name":"BLACK Elite V2 (12000 Puffs) Device (Battery)\t","category":"Devices","image":"http://localhost:5002/uploads/1728149944204.jpg","price":350,"branches":{"main":[{"name":"Gold","available":true,"_id":"670179b84a3e0cf85255d21e"},{"name":"Pink","available":true,"_id":"670179b84a3e0cf85255d21f"},{"name":"Green","available":true,"_id":"670179b84a3e0cf85255d220"},{"name":"Black","available":true,"_id":"670179b84a3e0cf85255d221"}],"second":[{"name":"Gold","available":true,"_id":"670179b84a3e0cf85255d222"},{"name":"Pink","available":true,"_id":"670179b84a3e0cf85255d223"},{"name":"Green","available":true,"_id":"670179b84a3e0cf85255d224"},{"name":"Black","available":true,"_id":"670179b84a3e0cf85255d225"}],"third":[{"name":"Gold","available":true,"_id":"670179b84a3e0cf85255d226"},{"name":"Pink","available":true,"_id":"670179b84a3e0cf85255d227"},{"name":"Green","available":true,"_id":"670179b84a3e0cf85255d228"},{"name":"Black","available":true,"_id":"670179b84a3e0cf85255d229"}],"_id":"670179b84a3e0cf85255d21d"},"__v":0},{"_id":"67017a1d4a3e0cf85255d46d","name":"SMUG Prime (12000 Puffs) Pod","category":"Pods","image":"http://localhost:5002/uploads/1728150045368.jpg","price":350,"branches":{"main":[{"name":"Very Baguio - Strawberry","available":true,"_id":"67017a1d4a3e0cf85255d46f"},{"name":"Red Cannon - Bubblegum","available":true,"_id":"67017a1d4a3e0cf85255d470"},{"name":"Bacteria Monster - Yakult","available":false,"_id":"67017a1d4a3e0cf85255d471"},{"name":"Cheer Blast - Lychee","available":true,"_id":"67017a1d4a3e0cf85255d472"},{"name":"Very More - Mixed Berries","available":true,"_id":"67017a1d4a3e0cf85255d473"},{"name":"Black Wave - Black Currant","available":true,"_id":"67017a1d4a3e0cf85255d474"},{"name":"Pitch Perfect - Honey Peach","available":true,"_id":"67017a1d4a3e0cf85255d475"},{"name":"Sparkle Squeeze - Lemon Cola","available":true,"_id":"67017a1d4a3e0cf85255d476"},{"name":"Blue Freeze - Blueberry Ice","available":true,"_id":"67017a1d4a3e0cf85255d477"},{"name":"Red Pulp - Watermelon","available":false,"_id":"67017a1d4a3e0cf85255d478"},{"name":"Trouble Purple - Grapes","available":true,"_id":"67017a1d4a3e0cf85255d479"},{"name":"Menthol Fresh - Mint","available":false,"_id":"67017a1d4a3e0cf85255d47a"},{"name":"Monkey Ice - Banana Ice\t","available":false,"_id":"67017a1d4a3e0cf85255d47b"},{"name":"Beer Sparkle - Rootbeer","available":true,"_id":"67017a1d4a3e0cf85255d47c"}],"second":[{"name":"Very Baguio - Strawberry","available":false,"_id":"67017a1d4a3e0cf85255d47d"},{"name":"Red Cannon - Bubblegum","available":true,"_id":"67017a1d4a3e0cf85255d47e"},{"name":"Bacteria Monster - Yakult","available":false,"_id":"67017a1d4a3e0cf85255d47f"},{"name":"Cheer Blast - Lychee","available":true,"_id":"67017a1d4a3e0cf85255d480"},{"name":"Very More - Mixed Berries","available":true,"_id":"67017a1d4a3e0cf85255d481"},{"name":"Black Wave - Black Currant","available":false,"_id":"67017a1d4a3e0cf85255d482"},{"name":"Pitch Perfect - Honey Peach","available":true,"_id":"67017a1d4a3e0cf85255d483"},{"name":"Sparkle Squeeze - Lemon Cola","available":true,"_id":"67017a1d4a3e0cf85255d484"},{"name":"Blue Freeze - Blueberry Ice","available":false,"_id":"67017a1d4a3e0cf85255d485"},{"name":"Red Pulp - Watermelon","available":false,"_id":"67017a1d4a3e0cf85255d486"},{"name":"Trouble Purple - Grapes","available":false,"_id":"67017a1d4a3e0cf85255d487"},{"name":"Menthol Fresh - Mint","available":false,"_id":"67017a1d4a3e0cf85255d488"},{"name":"Monkey Ice - Banana Ice\t","available":false,"_id":"67017a1d4a3e0cf85255d489"},{"name":"Beer Sparkle - Rootbeer","available":true,"_id":"67017a1d4a3e0cf85255d48a"}],"third":[{"name":"Very Baguio - Strawberry","available":false,"_id":"67017a1d4a3e0cf85255d48b"},{"name":"Red Cannon - Bubblegum","available":true,"_id":"67017a1d4a3e0cf85255d48c"},{"name":"Bacteria Monster - Yakult","available":false,"_id":"67017a1d4a3e0cf85255d48d"},{"name":"Cheer Blast - Lychee","available":true,"_id":"67017a1d4a3e0cf85255d48e"},{"name":"Very More - Mixed Berries","available":true,"_id":"67017a1d4a3e0cf85255d48f"},{"name":"Black Wave - Black Currant","available":true,"_id":"67017a1d4a3e0cf85255d490"},{"name":"Pitch Perfect - Honey Peach","available":true,"_id":"67017a1d4a3e0cf85255d491"},{"name":"Sparkle Squeeze - Lemon Cola","available":true,"_id":"67017a1d4a3e0cf85255d492"},{"name":"Blue Freeze - Blueberry Ice","available":true,"_id":"67017a1d4a3e0cf85255d493"},{"name":"Red Pulp - Watermelon","available":false,"_id":"67017a1d4a3e0cf85255d494"},{"name":"Trouble Purple - Grapes","available":false,"_id":"67017a1d4a3e0cf85255d495"},{"name":"Menthol Fresh - Mint","available":false,"_id":"67017a1d4a3e0cf85255d496"},{"name":"Monkey Ice - Banana Ice\t","available":false,"_id":"67017a1d4a3e0cf85255d497"},{"name":"Beer Sparkle - Rootbeer","available":true,"_id":"67017a1d4a3e0cf85255d498"}],"_id":"67017a1d4a3e0cf85255d46e"},"__v":0},{"_id":"67017bfe4a3e0cf85255d730","name":"SHIFT X Chillax VISTA","category":"Disposables","image":"http://localhost:5002/uploads/1728150526005.jpg","price":550,"branches":{"main":[{"name":"Grapes Bubblegum","available":false,"_id":"67017bfe4a3e0cf85255d732"},{"name":"Ice Lychee","available":true,"_id":"67017bfe4a3e0cf85255d733"},{"name":"Mint Ice","available":true,"_id":"67017bfe4a3e0cf85255d734"},{"name":"Ice Grapes","available":false,"_id":"67017bfe4a3e0cf85255d735"},{"name":"Strawberry Ice","available":false,"_id":"67017bfe4a3e0cf85255d736"},{"name":"Watermelon Strawberry","available":false,"_id":"67017bfe4a3e0cf85255d737"},{"name":"Watermelon Lychee","available":true,"_id":"67017bfe4a3e0cf85255d738"},{"name":"Bubblegum","available":true,"_id":"67017bfe4a3e0cf85255d739"},{"name":"Bubblegum","available":true,"_id":"67017bfe4a3e0cf85255d73a"},{"name":"Ice Cantaloupe","available":true,"_id":"67017bfe4a3e0cf85255d73b"},{"name":"Watermelon Bubblegum","available":true,"_id":"67017bfe4a3e0cf85255d73c"},{"name":"Mango Peach","available":true,"_id":"67017bfe4a3e0cf85255d73d"},{"name":"Ribena Ice","available":true,"_id":"67017bfe4a3e0cf85255d73e"},{"name":"Sour Apple","available":true,"_id":"67017bfe4a3e0cf85255d73f"},{"name":"Orange Juice","available":true,"_id":"67017bfe4a3e0cf85255d740"},{"name":"Strawberry Slush","available":true,"_id":"67017bfe4a3e0cf85255d741"},{"name":"Iced Matcha","available":true,"_id":"67017bfe4a3e0cf85255d742"},{"name":"Watermelon Ice","available":false,"_id":"67017bfe4a3e0cf85255d743"},{"name":"Nerdz Candy","available":true,"_id":"67017bfe4a3e0cf85255d744"},{"name":"Strawberry Blackcurrant","available":true,"_id":"67017bfe4a3e0cf85255d745"},{"name":"Gummy Bears","available":true,"_id":"67017bfe4a3e0cf85255d746"},{"name":"Mango Peach","available":true,"_id":"67017bfe4a3e0cf85255d747"}],"second":[{"name":"Grapes Bubblegum","available":true,"_id":"67017bfe4a3e0cf85255d748"},{"name":"Ice Lychee","available":true,"_id":"67017bfe4a3e0cf85255d749"},{"name":"Mint Ice","available":true,"_id":"67017bfe4a3e0cf85255d74a"},{"name":"Ice Grapes","available":false,"_id":"67017bfe4a3e0cf85255d74b"},{"name":"Strawberry Ice","available":false,"_id":"67017bfe4a3e0cf85255d74c"},{"name":"Watermelon Strawberry","available":false,"_id":"67017bfe4a3e0cf85255d74d"},{"name":"Watermelon Lychee","available":true,"_id":"67017bfe4a3e0cf85255d74e"},{"name":"Bubblegum","available":true,"_id":"67017bfe4a3e0cf85255d74f"},{"name":"Bubblegum","available":true,"_id":"67017bfe4a3e0cf85255d750"},{"name":"Ice Cantaloupe","available":true,"_id":"67017bfe4a3e0cf85255d751"},{"name":"Watermelon Bubblegum","available":true,"_id":"67017bfe4a3e0cf85255d752"},{"name":"Mango Peach","available":true,"_id":"67017bfe4a3e0cf85255d753"},{"name":"Ribena Ice","available":true,"_id":"67017bfe4a3e0cf85255d754"},{"name":"Sour Apple","available":true,"_id":"67017bfe4a3e0cf85255d755"},{"name":"Orange Juice","available":true,"_id":"67017bfe4a3e0cf85255d756"},{"name":"Strawberry Slush","available":true,"_id":"67017bfe4a3e0cf85255d757"},{"name":"Iced Matcha","available":true,"_id":"67017bfe4a3e0cf85255d758"},{"name":"Watermelon Ice","available":true,"_id":"67017bfe4a3e0cf85255d759"},{"name":"Nerdz Candy","available":true,"_id":"67017bfe4a3e0cf85255d75a"},{"name":"Strawberry Blackcurrant","available":true,"_id":"67017bfe4a3e0cf85255d75b"},{"name":"Gummy Bears","available":true,"_id":"67017bfe4a3e0cf85255d75c"},{"name":"Mango Peach","available":true,"_id":"67017bfe4a3e0cf85255d75d"}],"third":[{"name":"Grapes Bubblegum","available":false,"_id":"67017bfe4a3e0cf85255d75e"},{"name":"Ice Lychee","available":true,"_id":"67017bfe4a3e0cf85255d75f"},{"name":"Mint Ice","available":true,"_id":"67017bfe4a3e0cf85255d760"},{"name":"Ice Grapes","available":true,"_id":"67017bfe4a3e0cf85255d761"},{"name":"Strawberry Ice","available":false,"_id":"67017bfe4a3e0cf85255d762"},{"name":"Watermelon Strawberry","available":false,"_id":"67017bfe4a3e0cf85255d763"},{"name":"Watermelon Lychee","available":true,"_id":"67017bfe4a3e0cf85255d764"},{"name":"Bubblegum","available":true,"_id":"67017bfe4a3e0cf85255d765"},{"name":"Bubblegum","available":true,"_id":"67017bfe4a3e0cf85255d766"},{"name":"Ice Cantaloupe","available":true,"_id":"67017bfe4a3e0cf85255d767"},{"name":"Watermelon Bubblegum","available":true,"_id":"67017bfe4a3e0cf85255d768"},{"name":"Mango Peach","available":true,"_id":"67017bfe4a3e0cf85255d769"},{"name":"Ribena Ice","available":true,"_id":"67017bfe4a3e0cf85255d76a"},{"name":"Sour Apple","available":true,"_id":"67017bfe4a3e0cf85255d76b"},{"name":"Orange Juice","available":true,"_id":"67017bfe4a3e0cf85255d76c"},{"name":"Strawberry Slush","available":false,"_id":"67017bfe4a3e0cf85255d76d"},{"name":"Iced Matcha","available":true,"_id":"67017bfe4a3e0cf85255d76e"},{"name":"Watermelon Ice","available":false,"_id":"67017bfe4a3e0cf85255d76f"},{"name":"Nerdz Candy","available":true,"_id":"67017bfe4a3e0cf85255d770"},{"name":"Strawberry Blackcurrant","available":true,"_id":"67017bfe4a3e0cf85255d771"},{"name":"Gummy Bears","available":true,"_id":"67017bfe4a3e0cf85255d772"},{"name":"Mango Peach","available":true,"_id":"67017bfe4a3e0cf85255d773"}],"_id":"67017bfe4a3e0cf85255d731"},"__v":0},{"_id":"67017c5f4a3e0cf85255da8f","name":"X-Vape X1 Series (10000 Puffs)","category":"Disposables","image":"http://localhost:5002/uploads/1728150623975.jpg","price":551,"branches":{"main":[{"name":"Black Tornado - Black Currant","available":true,"_id":"67017c5f4a3e0cf85255da91"},{"name":"Brown Valley - Brandy Chocolate","available":true,"_id":"67017c5f4a3e0cf85255da92"},{"name":"Fresh Forest - Supermint","available":true,"_id":"67017c5f4a3e0cf85255da93"},{"name":"Pink Air - Melon Yakult","available":true,"_id":"67017c5f4a3e0cf85255da94"},{"name":"Polar Glacier - Lychee Ice","available":true,"_id":"67017c5f4a3e0cf85255da95"},{"name":"Red Tide - Cherry Coke","available":true,"_id":"67017c5f4a3e0cf85255da96"},{"name":"Tropical Storm - Triple Mango","available":true,"_id":"67017c5f4a3e0cf85255da97"},{"name":"Rich Mist - Hazelnut Coffee","available":true,"_id":"67017c5f4a3e0cf85255da98"}],"second":[{"name":"Black Tornado - Black Currant","available":true,"_id":"67017c5f4a3e0cf85255da99"},{"name":"Brown Valley - Brandy Chocolate","available":true,"_id":"67017c5f4a3e0cf85255da9a"},{"name":"Fresh Forest - Supermint","available":true,"_id":"67017c5f4a3e0cf85255da9b"},{"name":"Pink Air - Melon Yakult","available":true,"_id":"67017c5f4a3e0cf85255da9c"},{"name":"Polar Glacier - Lychee Ice","available":true,"_id":"67017c5f4a3e0cf85255da9d"},{"name":"Red Tide - Cherry Coke","available":true,"_id":"67017c5f4a3e0cf85255da9e"},{"name":"Tropical Storm - Triple Mango","available":true,"_id":"67017c5f4a3e0cf85255da9f"},{"name":"Rich Mist - Hazelnut Coffee","available":true,"_id":"67017c5f4a3e0cf85255daa0"}],"third":[{"name":"Black Tornado - Black Currant","available":true,"_id":"67017c5f4a3e0cf85255daa1"},{"name":"Brown Valley - Brandy Chocolate","available":true,"_id":"67017c5f4a3e0cf85255daa2"},{"name":"Fresh Forest - Supermint","available":true,"_id":"67017c5f4a3e0cf85255daa3"},{"name":"Pink Air - Melon Yakult","available":true,"_id":"67017c5f4a3e0cf85255daa4"},{"name":"Polar Glacier - Lychee Ice","available":true,"_id":"67017c5f4a3e0cf85255daa5"},{"name":"Red Tide - Cherry Coke","available":true,"_id":"67017c5f4a3e0cf85255daa6"},{"name":"Tropical Storm - Triple Mango","available":true,"_id":"67017c5f4a3e0cf85255daa7"},{"name":"Rich Mist - Hazelnut Coffee","available":true,"_id":"67017c5f4a3e0cf85255daa8"}],"_id":"67017c5f4a3e0cf85255da90"},"__v":0},{"_id":"67017caa4a3e0cf85255e13e","name":"X-Vape X3 Series (10000 Puffs)","category":"Disposables","image":"http://localhost:5002/uploads/1728150698577.jpg","price":699,"branches":{"main":[{"name":"Tropical Storm - Triple Mango","available":true,"_id":"67017caa4a3e0cf85255e140"},{"name":"Fresh Forest - Super Mint","available":true,"_id":"67017caa4a3e0cf85255e141"},{"name":"Pink Air - Melon Yakult","available":true,"_id":"67017caa4a3e0cf85255e142"},{"name":"Brown Valley - Brancy Chocolate","available":true,"_id":"67017caa4a3e0cf85255e143"},{"name":"Rich Mist - Hazelnut Coffee","available":true,"_id":"67017caa4a3e0cf85255e144"},{"name":"Red Tide - Cherry Coke","available":true,"_id":"67017caa4a3e0cf85255e145"},{"name":"Black Tornado - Black Currant","available":true,"_id":"67017caa4a3e0cf85255e146"},{"name":"Black Tornado - Black Currant","available":true,"_id":"67017caa4a3e0cf85255e147"}],"second":[{"name":"Tropical Storm - Triple Mango","available":true,"_id":"67017caa4a3e0cf85255e148"},{"name":"Fresh Forest - Super Mint","available":true,"_id":"67017caa4a3e0cf85255e149"},{"name":"Pink Air - Melon Yakult","available":true,"_id":"67017caa4a3e0cf85255e14a"},{"name":"Brown Valley - Brancy Chocolate","available":true,"_id":"67017caa4a3e0cf85255e14b"},{"name":"Rich Mist - Hazelnut Coffee","available":true,"_id":"67017caa4a3e0cf85255e14c"},{"name":"Red Tide - Cherry Coke","available":true,"_id":"67017caa4a3e0cf85255e14d"},{"name":"Black Tornado - Black Currant","available":true,"_id":"67017caa4a3e0cf85255e14e"},{"name":"Black Tornado - Black Currant","available":true,"_id":"67017caa4a3e0cf85255e14f"}],"third":[{"name":"Tropical Storm - Triple Mango","available":true,"_id":"67017caa4a3e0cf85255e150"},{"name":"Fresh Forest - Super Mint","available":true,"_id":"67017caa4a3e0cf85255e151"},{"name":"Pink Air - Melon Yakult","available":true,"_id":"67017caa4a3e0cf85255e152"},{"name":"Brown Valley - Brancy Chocolate","available":true,"_id":"67017caa4a3e0cf85255e153"},{"name":"Rich Mist - Hazelnut Coffee","available":true,"_id":"67017caa4a3e0cf85255e154"},{"name":"Red Tide - Cherry Coke","available":true,"_id":"67017caa4a3e0cf85255e155"},{"name":"Black Tornado - Black Currant","available":true,"_id":"67017caa4a3e0cf85255e156"},{"name":"Black Tornado - Black Currant","available":true,"_id":"67017caa4a3e0cf85255e157"}],"_id":"67017caa4a3e0cf85255e13f"},"__v":0},{"_id":"67017cee4a3e0cf85255e84d","name":"X-Vape X5 Series (10000 Puffs)","category":"Disposables","image":"http://localhost:5002/uploads/1728150766433.jpg","price":730,"branches":{"main":[{"name":"Tropical Storm - Triple Mango","available":true,"_id":"67017cee4a3e0cf85255e84f"},{"name":"Fresh Forest - Super Mint","available":true,"_id":"67017cee4a3e0cf85255e850"},{"name":"Pink Air - Melon Yakult","available":true,"_id":"67017cee4a3e0cf85255e851"},{"name":"Brown Valley - Brancy Chocolate","available":true,"_id":"67017cee4a3e0cf85255e852"},{"name":"Rich Mist - Hazelnut Coffee","available":true,"_id":"67017cee4a3e0cf85255e853"},{"name":"Red Tide - Cherry Coke","available":true,"_id":"67017cee4a3e0cf85255e854"},{"name":"Black Tornado - Black Currant","available":true,"_id":"67017cee4a3e0cf85255e855"},{"name":"Polar Gracier - Lychee Ice","available":true,"_id":"67017cee4a3e0cf85255e856"}],"second":[{"name":"Tropical Storm - Triple Mango","available":true,"_id":"67017cee4a3e0cf85255e857"},{"name":"Fresh Forest - Super Mint","available":true,"_id":"67017cee4a3e0cf85255e858"},{"name":"Pink Air - Melon Yakult","available":true,"_id":"67017cee4a3e0cf85255e859"},{"name":"Brown Valley - Brancy Chocolate","available":true,"_id":"67017cee4a3e0cf85255e85a"},{"name":"Rich Mist - Hazelnut Coffee","available":true,"_id":"67017cee4a3e0cf85255e85b"},{"name":"Red Tide - Cherry Coke","available":true,"_id":"67017cee4a3e0cf85255e85c"},{"name":"Black Tornado - Black Currant","available":true,"_id":"67017cee4a3e0cf85255e85d"},{"name":"Polar Gracier - Lychee Ice","available":true,"_id":"67017cee4a3e0cf85255e85e"}],"third":[{"name":"Tropical Storm - Triple Mango","available":true,"_id":"67017cee4a3e0cf85255e85f"},{"name":"Fresh Forest - Super Mint","available":true,"_id":"67017cee4a3e0cf85255e860"},{"name":"Pink Air - Melon Yakult","available":true,"_id":"67017cee4a3e0cf85255e861"},{"name":"Brown Valley - Brancy Chocolate","available":true,"_id":"67017cee4a3e0cf85255e862"},{"name":"Rich Mist - Hazelnut Coffee","available":true,"_id":"67017cee4a3e0cf85255e863"},{"name":"Red Tide - Cherry Coke","available":true,"_id":"67017cee4a3e0cf85255e864"},{"name":"Black Tornado - Black Currant","available":true,"_id":"67017cee4a3e0cf85255e865"},{"name":"Polar Gracier - Lychee Ice","available":true,"_id":"67017cee4a3e0cf85255e866"}],"_id":"67017cee4a3e0cf85255e84e"},"__v":0},{"_id":"67017d344a3e0cf85255ec2c","name":"X-Vape X6 Series (10000 Puffs)","category":"Disposables","image":"http://localhost:5002/uploads/1728150836936.jpg","price":500,"branches":{"main":[{"name":"Tropical Storm - Triple Mango","available":true,"_id":"67017d344a3e0cf85255ec2e"},{"name":"Fresh Forest - Super Mint","available":true,"_id":"67017d344a3e0cf85255ec2f"},{"name":"Pink Air - Melon Yakult","available":true,"_id":"67017d344a3e0cf85255ec30"},{"name":"Brown Valley - Brancy Chocolate","available":true,"_id":"67017d344a3e0cf85255ec31"},{"name":"Rich Mist - Hazelnut Coffee","available":true,"_id":"67017d344a3e0cf85255ec32"},{"name":"Red Tide - Cherry Coke","available":true,"_id":"67017d344a3e0cf85255ec33"},{"name":"Black Tornado - Black Currant","available":true,"_id":"67017d344a3e0cf85255ec34"},{"name":"Polar Gracier - Lychee Ice","available":true,"_id":"67017d344a3e0cf85255ec35"}],"second":[{"name":"Tropical Storm - Triple Mango","available":true,"_id":"67017d344a3e0cf85255ec36"},{"name":"Fresh Forest - Super Mint","available":true,"_id":"67017d344a3e0cf85255ec37"},{"name":"Pink Air - Melon Yakult","available":true,"_id":"67017d344a3e0cf85255ec38"},{"name":"Brown Valley - Brancy Chocolate","available":true,"_id":"67017d344a3e0cf85255ec39"},{"name":"Rich Mist - Hazelnut Coffee","available":true,"_id":"67017d344a3e0cf85255ec3a"},{"name":"Red Tide - Cherry Coke","available":true,"_id":"67017d344a3e0cf85255ec3b"},{"name":"Black Tornado - Black Currant","available":true,"_id":"67017d344a3e0cf85255ec3c"},{"name":"Polar Gracier - Lychee Ice","available":true,"_id":"67017d344a3e0cf85255ec3d"}],"third":[{"name":"Tropical Storm - Triple Mango","available":true,"_id":"67017d344a3e0cf85255ec3e"},{"name":"Fresh Forest - Super Mint","available":true,"_id":"67017d344a3e0cf85255ec3f"},{"name":"Pink Air - Melon Yakult","available":true,"_id":"67017d344a3e0cf85255ec40"},{"name":"Brown Valley - Brancy Chocolate","available":true,"_id":"67017d344a3e0cf85255ec41"},{"name":"Rich Mist - Hazelnut Coffee","available":true,"_id":"67017d344a3e0cf85255ec42"},{"name":"Red Tide - Cherry Coke","available":true,"_id":"67017d344a3e0cf85255ec43"},{"name":"Black Tornado - Black Currant","available":true,"_id":"67017d344a3e0cf85255ec44"},{"name":"Polar Gracier - Lychee Ice","available":true,"_id":"67017d344a3e0cf85255ec45"}],"_id":"67017d344a3e0cf85255ec2d"},"__v":0},{"_id":"67017d7c4a3e0cf85255f021","name":"X-Vape X6 Series (10000 Puffs) Device (Battery)","category":"Devices","image":"http://localhost:5002/uploads/1728150908406.jpg","price":330,"branches":{"main":[{"name":"Black","available":true,"_id":"67017d7c4a3e0cf85255f023"},{"name":"Brown","available":true,"_id":"67017d7c4a3e0cf85255f024"},{"name":"Rose Gold","available":true,"_id":"67017d7c4a3e0cf85255f025"},{"name":"Red","available":true,"_id":"67017d7c4a3e0cf85255f026"},{"name":"Green","available":true,"_id":"67017d7c4a3e0cf85255f027"},{"name":"Yellow","available":true,"_id":"67017d7c4a3e0cf85255f028"},{"name":"Blue","available":true,"_id":"67017d7c4a3e0cf85255f029"},{"name":"Pink","available":true,"_id":"67017d7c4a3e0cf85255f02a"}],"second":[{"name":"Black","available":true,"_id":"67017d7c4a3e0cf85255f02b"},{"name":"Brown","available":true,"_id":"67017d7c4a3e0cf85255f02c"},{"name":"Rose Gold","available":true,"_id":"67017d7c4a3e0cf85255f02d"},{"name":"Red","available":true,"_id":"67017d7c4a3e0cf85255f02e"},{"name":"Green","available":true,"_id":"67017d7c4a3e0cf85255f02f"},{"name":"Yellow","available":true,"_id":"67017d7c4a3e0cf85255f030"},{"name":"Blue","available":true,"_id":"67017d7c4a3e0cf85255f031"},{"name":"Pink","available":true,"_id":"67017d7c4a3e0cf85255f032"}],"third":[{"name":"Black","available":true,"_id":"67017d7c4a3e0cf85255f033"},{"name":"Brown","available":true,"_id":"67017d7c4a3e0cf85255f034"},{"name":"Rose Gold","available":true,"_id":"67017d7c4a3e0cf85255f035"},{"name":"Red","available":true,"_id":"67017d7c4a3e0cf85255f036"},{"name":"Green","available":true,"_id":"67017d7c4a3e0cf85255f037"},{"name":"Yellow","available":true,"_id":"67017d7c4a3e0cf85255f038"},{"name":"Blue","available":true,"_id":"67017d7c4a3e0cf85255f039"},{"name":"Pink","available":true,"_id":"67017d7c4a3e0cf85255f03a"}],"_id":"67017d7c4a3e0cf85255f022"},"__v":0},{"_id":"67017dce4a3e0cf85255f446","name":"BLACK Elite Pod Formula (SaltNic 30ml)","category":"Juices","image":"http://localhost:5002/uploads/1728150990184.webp","price":400,"branches":{"main":[{"name":"Green Tokyo - Matcha","available":true,"_id":"67017dce4a3e0cf85255f448"},{"name":"Very More - Mix Berries","available":true,"_id":"67017dce4a3e0cf85255f449"},{"name":"Very Baguio - Strawberry","available":true,"_id":"67017dce4a3e0cf85255f44a"},{"name":"Rainbow Punch - Kool Aid","available":true,"_id":"67017dce4a3e0cf85255f44b"},{"name":"Trouble Purple - Grapes","available":true,"_id":"67017dce4a3e0cf85255f44c"},{"name":"Yellow Summer - Mango","available":true,"_id":"67017dce4a3e0cf85255f44d"},{"name":"Bacteria Monster Yakult","available":true,"_id":"67017dce4a3e0cf85255f44e"},{"name":"Bubble Blower - Bubblegum","available":true,"_id":"67017dce4a3e0cf85255f44f"},{"name":"Very Monkey - Strawberry Banana","available":true,"_id":"67017dce4a3e0cf85255f450"},{"name":"Fresh Menthol - Very Menthol","available":true,"_id":"67017dce4a3e0cf85255f451"},{"name":"Red Pulp - Watermelon Ice","available":true,"_id":"67017dce4a3e0cf85255f452"}],"second":[{"name":"Green Tokyo - Matcha","available":true,"_id":"67017dce4a3e0cf85255f453"},{"name":"Very More - Mix Berries","available":true,"_id":"67017dce4a3e0cf85255f454"},{"name":"Very Baguio - Strawberry","available":true,"_id":"67017dce4a3e0cf85255f455"},{"name":"Rainbow Punch - Kool Aid","available":true,"_id":"67017dce4a3e0cf85255f456"},{"name":"Trouble Purple - Grapes","available":true,"_id":"67017dce4a3e0cf85255f457"},{"name":"Yellow Summer - Mango","available":true,"_id":"67017dce4a3e0cf85255f458"},{"name":"Bacteria Monster Yakult","available":true,"_id":"67017dce4a3e0cf85255f459"},{"name":"Bubble Blower - Bubblegum","available":true,"_id":"67017dce4a3e0cf85255f45a"},{"name":"Very Monkey - Strawberry Banana","available":true,"_id":"67017dce4a3e0cf85255f45b"},{"name":"Fresh Menthol - Very Menthol","available":true,"_id":"67017dce4a3e0cf85255f45c"},{"name":"Red Pulp - Watermelon Ice","available":true,"_id":"67017dce4a3e0cf85255f45d"}],"third":[{"name":"Green Tokyo - Matcha","available":true,"_id":"67017dce4a3e0cf85255f45e"},{"name":"Very More - Mix Berries","available":true,"_id":"67017dce4a3e0cf85255f45f"},{"name":"Very Baguio - Strawberry","available":true,"_id":"67017dce4a3e0cf85255f460"},{"name":"Rainbow Punch - Kool Aid","available":true,"_id":"67017dce4a3e0cf85255f461"},{"name":"Trouble Purple - Grapes","available":true,"_id":"67017dce4a3e0cf85255f462"},{"name":"Yellow Summer - Mango","available":true,"_id":"67017dce4a3e0cf85255f463"},{"name":"Bacteria Monster Yakult","available":true,"_id":"67017dce4a3e0cf85255f464"},{"name":"Bubble Blower - Bubblegum","available":true,"_id":"67017dce4a3e0cf85255f465"},{"name":"Very Monkey - Strawberry Banana","available":true,"_id":"67017dce4a3e0cf85255f466"},{"name":"Fresh Menthol - Very Menthol","available":true,"_id":"67017dce4a3e0cf85255f467"},{"name":"Red Pulp - Watermelon Ice","available":true,"_id":"67017dce4a3e0cf85255f468"}],"_id":"67017dce4a3e0cf85255f447"},"__v":0},{"_id":"67017e034a3e0cf85255f8b6","name":"RELX Infinity 2 Device","category":"Devices","image":"http://localhost:5002/uploads/1728151043853.webp","price":850,"branches":{"main":[{"name":"Green Navy","available":true,"_id":"67017e034a3e0cf85255f8b8"},{"name":"Cherry Blossom","available":false,"_id":"67017e034a3e0cf85255f8b9"},{"name":"Dark Asteroid","available":false,"_id":"67017e034a3e0cf85255f8ba"},{"name":"Royal Indigo","available":false,"_id":"67017e034a3e0cf85255f8bb"},{"name":"Blue Bay","available":true,"_id":"67017e034a3e0cf85255f8bc"},{"name":"Obsidian Black","available":false,"_id":"67017e034a3e0cf85255f8bd"}],"second":[{"name":"Green Navy","available":true,"_id":"67017e034a3e0cf85255f8be"},{"name":"Cherry Blossom","available":false,"_id":"67017e034a3e0cf85255f8bf"},{"name":"Dark Asteroid","available":false,"_id":"67017e034a3e0cf85255f8c0"},{"name":"Royal Indigo","available":true,"_id":"67017e034a3e0cf85255f8c1"},{"name":"Blue Bay","available":true,"_id":"67017e034a3e0cf85255f8c2"},{"name":"Obsidian Black","available":false,"_id":"67017e034a3e0cf85255f8c3"}],"third":[{"name":"Green Navy","available":true,"_id":"67017e034a3e0cf85255f8c4"},{"name":"Cherry Blossom","available":false,"_id":"67017e034a3e0cf85255f8c5"},{"name":"Dark Asteroid","available":false,"_id":"67017e034a3e0cf85255f8c6"},{"name":"Royal Indigo","available":true,"_id":"67017e034a3e0cf85255f8c7"},{"name":"Blue Bay","available":true,"_id":"67017e034a3e0cf85255f8c8"},{"name":"Obsidian Black","available":false,"_id":"67017e034a3e0cf85255f8c9"}],"_id":"67017e034a3e0cf85255f8b7"},"__v":0},{"_id":"67017e344a3e0cf8525601d1","name":"RELX Artisan Device","category":"Devices","image":"http://localhost:5002/uploads/1728151092653.jpg","price":1300,"branches":{"main":[{"name":"Black Wave","available":false,"_id":"67017e344a3e0cf8525601d3"},{"name":"Silver Wave","available":true,"_id":"67017e344a3e0cf8525601d4"},{"name":"Hammered Steel","available":true,"_id":"67017e344a3e0cf8525601d5"},{"name":"Indigo Denim","available":true,"_id":"67017e344a3e0cf8525601d6"},{"name":"Bright Mandarin","available":true,"_id":"67017e344a3e0cf8525601d7"},{"name":"Royal Saddle","available":true,"_id":"67017e344a3e0cf8525601d8"},{"name":"Robin Blue","available":true,"_id":"67017e344a3e0cf8525601d9"}],"second":[{"name":"Black Wave","available":true,"_id":"67017e344a3e0cf8525601da"},{"name":"Silver Wave","available":true,"_id":"67017e344a3e0cf8525601db"},{"name":"Hammered Steel","available":true,"_id":"67017e344a3e0cf8525601dc"},{"name":"Indigo Denim","available":false,"_id":"67017e344a3e0cf8525601dd"},{"name":"Bright Mandarin","available":true,"_id":"67017e344a3e0cf8525601de"},{"name":"Royal Saddle","available":true,"_id":"67017e344a3e0cf8525601df"},{"name":"Robin Blue","available":true,"_id":"67017e344a3e0cf8525601e0"}],"third":[{"name":"Black Wave","available":true,"_id":"67017e344a3e0cf8525601e1"},{"name":"Silver Wave","available":true,"_id":"67017e344a3e0cf8525601e2"},{"name":"Hammered Steel","available":true,"_id":"67017e344a3e0cf8525601e3"},{"name":"Indigo Denim","available":true,"_id":"67017e344a3e0cf8525601e4"},{"name":"Bright Mandarin","available":true,"_id":"67017e344a3e0cf8525601e5"},{"name":"Royal Saddle","available":true,"_id":"67017e344a3e0cf8525601e6"},{"name":"Robin Blue","available":true,"_id":"67017e344a3e0cf8525601e7"}],"_id":"67017e344a3e0cf8525601d2"},"__v":0},{"_id":"67017e6b4a3e0cf852560683","name":"OXVA SQ Pro","category":"Devices","image":"http://localhost:5002/uploads/1728151147987.jpg","price":1000,"branches":{"main":[{"name":"Gun Metal Wood","available":false,"_id":"67017e6b4a3e0cf852560685"},{"name":"Spring White","available":true,"_id":"67017e6b4a3e0cf852560686"},{"name":"Bronze Wood","available":true,"_id":"67017e6b4a3e0cf852560687"},{"name":"Pink Pastel","available":false,"_id":"67017e6b4a3e0cf852560688"},{"name":"Black Carbon","available":true,"_id":"67017e6b4a3e0cf852560689"},{"name":"Gold Carbon","available":true,"_id":"67017e6b4a3e0cf85256068a"},{"name":"Muave White","available":true,"_id":"67017e6b4a3e0cf85256068b"},{"name":"Gentle Blue","available":true,"_id":"67017e6b4a3e0cf85256068c"}],"second":[{"name":"Gun Metal Wood","available":true,"_id":"67017e6b4a3e0cf85256068d"},{"name":"Spring White","available":true,"_id":"67017e6b4a3e0cf85256068e"},{"name":"Bronze Wood","available":false,"_id":"67017e6b4a3e0cf85256068f"},{"name":"Pink Pastel","available":true,"_id":"67017e6b4a3e0cf852560690"},{"name":"Black Carbon","available":true,"_id":"67017e6b4a3e0cf852560691"},{"name":"Gold Carbon","available":true,"_id":"67017e6b4a3e0cf852560692"},{"name":"Muave White","available":true,"_id":"67017e6b4a3e0cf852560693"},{"name":"Gentle Blue","available":true,"_id":"67017e6b4a3e0cf852560694"}],"third":[{"name":"Gun Metal Wood","available":true,"_id":"67017e6b4a3e0cf852560695"},{"name":"Spring White","available":true,"_id":"67017e6b4a3e0cf852560696"},{"name":"Bronze Wood","available":true,"_id":"67017e6b4a3e0cf852560697"},{"name":"Pink Pastel","available":true,"_id":"67017e6b4a3e0cf852560698"},{"name":"Black Carbon","available":true,"_id":"67017e6b4a3e0cf852560699"},{"name":"Gold Carbon","available":true,"_id":"67017e6b4a3e0cf85256069a"},{"name":"Muave White","available":true,"_id":"67017e6b4a3e0cf85256069b"},{"name":"Gentle Blue","available":true,"_id":"67017e6b4a3e0cf85256069c"}],"_id":"67017e6b4a3e0cf852560684"},"__v":0},{"_id":"67017ea04a3e0cf852560b68","name":"OXVA Xlim Go","category":"Devices","image":"http://localhost:5002/uploads/1728151200403.jpg","price":598,"branches":{"main":[{"name":"Pink","available":false,"_id":"67017ea04a3e0cf852560b6a"},{"name":"Red","available":false,"_id":"67017ea04a3e0cf852560b6b"},{"name":"White","available":false,"_id":"67017ea04a3e0cf852560b6c"},{"name":"Light Green","available":false,"_id":"67017ea04a3e0cf852560b6d"},{"name":"Light Brown","available":false,"_id":"67017ea04a3e0cf852560b6e"},{"name":"Dark Brown","available":false,"_id":"67017ea04a3e0cf852560b6f"},{"name":"Dark Gray","available":false,"_id":"67017ea04a3e0cf852560b70"}],"second":[{"name":"Pink","available":false,"_id":"67017ea04a3e0cf852560b71"},{"name":"Red","available":false,"_id":"67017ea04a3e0cf852560b72"},{"name":"White","available":false,"_id":"67017ea04a3e0cf852560b73"},{"name":"Light Green","available":true,"_id":"67017ea04a3e0cf852560b74"},{"name":"Light Brown","available":false,"_id":"67017ea04a3e0cf852560b75"},{"name":"Dark Brown","available":false,"_id":"67017ea04a3e0cf852560b76"},{"name":"Dark Gray","available":false,"_id":"67017ea04a3e0cf852560b77"}],"third":[{"name":"Pink","available":true,"_id":"67017ea04a3e0cf852560b78"},{"name":"Red","available":false,"_id":"67017ea04a3e0cf852560b79"},{"name":"White","available":false,"_id":"67017ea04a3e0cf852560b7a"},{"name":"Light Green","available":false,"_id":"67017ea04a3e0cf852560b7b"},{"name":"Light Brown","available":false,"_id":"67017ea04a3e0cf852560b7c"},{"name":"Dark Brown","available":false,"_id":"67017ea04a3e0cf852560b7d"},{"name":"Dark Gray","available":false,"_id":"67017ea04a3e0cf852560b7e"}],"_id":"67017ea04a3e0cf852560b69"},"__v":0},{"_id":"67017ecc4a3e0cf852561074","name":"IQOS TEREA","category":"Misc","image":"http://localhost:5002/uploads/1728151244041.jpg","price":140,"branches":{"main":[{"name":"Purple Wave","available":true,"_id":"67017ecc4a3e0cf852561076"},{"name":"Blue","available":true,"_id":"67017ecc4a3e0cf852561077"},{"name":"Yellow","available":true,"_id":"67017ecc4a3e0cf852561078"},{"name":"Amber","available":true,"_id":"67017ecc4a3e0cf852561079"},{"name":"Bronze","available":true,"_id":"67017ecc4a3e0cf85256107a"},{"name":"Green","available":true,"_id":"67017ecc4a3e0cf85256107b"}],"second":[{"name":"Purple Wave","available":true,"_id":"67017ecc4a3e0cf85256107c"},{"name":"Blue","available":true,"_id":"67017ecc4a3e0cf85256107d"},{"name":"Yellow","available":true,"_id":"67017ecc4a3e0cf85256107e"},{"name":"Amber","available":true,"_id":"67017ecc4a3e0cf85256107f"},{"name":"Bronze","available":true,"_id":"67017ecc4a3e0cf852561080"},{"name":"Green","available":true,"_id":"67017ecc4a3e0cf852561081"}],"third":[{"name":"Purple Wave","available":true,"_id":"67017ecc4a3e0cf852561082"},{"name":"Blue","available":true,"_id":"67017ecc4a3e0cf852561083"},{"name":"Yellow","available":true,"_id":"67017ecc4a3e0cf852561084"},{"name":"Amber","available":true,"_id":"67017ecc4a3e0cf852561085"},{"name":"Bronze","available":true,"_id":"67017ecc4a3e0cf852561086"},{"name":"Green","available":true,"_id":"67017ecc4a3e0cf852561087"}],"_id":"67017ecc4a3e0cf852561075"},"__v":0},{"_id":"67017eee4a3e0cf8525615a1","name":"ZYN Can","category":"Misc","image":"http://localhost:5002/uploads/1728151278483.jpg","price":140,"branches":{"main":[{"name":"Sunrise Can 3mg","available":true,"_id":"67017eee4a3e0cf8525615a3"},{"name":"Sunrise Can 6mg","available":true,"_id":"67017eee4a3e0cf8525615a4"},{"name":"Cool Breeze 3mg","available":true,"_id":"67017eee4a3e0cf8525615a5"},{"name":"Cool Breeze 6mg","available":true,"_id":"67017eee4a3e0cf8525615a6"}],"second":[{"name":"Sunrise Can 3mg","available":true,"_id":"67017eee4a3e0cf8525615a7"},{"name":"Sunrise Can 6mg","available":true,"_id":"67017eee4a3e0cf8525615a8"},{"name":"Cool Breeze 3mg","available":true,"_id":"67017eee4a3e0cf8525615a9"},{"name":"Cool Breeze 6mg","available":true,"_id":"67017eee4a3e0cf8525615aa"}],"third":[{"name":"Sunrise Can 3mg","available":true,"_id":"67017eee4a3e0cf8525615ab"},{"name":"Sunrise Can 6mg","available":true,"_id":"67017eee4a3e0cf8525615ac"},{"name":"Cool Breeze 3mg","available":true,"_id":"67017eee4a3e0cf8525615ad"},{"name":"Cool Breeze 6mg","available":true,"_id":"67017eee4a3e0cf8525615ae"}],"_id":"67017eee4a3e0cf8525615a2"},"__v":0},{"_id":"67017f2a4a3e0cf852561ae0","name":"Chillax Vista Mini","category":"Disposables","image":"http://localhost:5002/uploads/1728151338461.jpg","price":200,"branches":{"main":[{"name":"Lime Mint","available":true,"_id":"67017f2a4a3e0cf852561ae2"},{"name":"Sea Salt Lemon","available":false,"_id":"67017f2a4a3e0cf852561ae3"},{"name":"Strawberry Kiwi","available":false,"_id":"67017f2a4a3e0cf852561ae4"}],"second":[{"name":"Lime Mint","available":true,"_id":"67017f2a4a3e0cf852561ae5"},{"name":"Sea Salt Lemon","available":false,"_id":"67017f2a4a3e0cf852561ae6"},{"name":"Strawberry Kiwi","available":false,"_id":"67017f2a4a3e0cf852561ae7"}],"third":[{"name":"Lime Mint","available":true,"_id":"67017f2a4a3e0cf852561ae8"},{"name":"Sea Salt Lemon","available":false,"_id":"67017f2a4a3e0cf852561ae9"},{"name":"Strawberry Kiwi","available":false,"_id":"67017f2a4a3e0cf852561aea"}],"_id":"67017f2a4a3e0cf852561ae1"},"__v":0},{"_id":"67017f734a3e0cf85256202e","name":"BLACK Elite V1 Device (Battery)","category":"Devices","image":"http://localhost:5002/uploads/1728151411457.jpg","price":250,"branches":{"main":[{"name":"Battery","available":true,"_id":"67017f734a3e0cf852562030"}],"second":[{"name":"Battery","available":true,"_id":"67017f734a3e0cf852562031"}],"third":[{"name":"Battery","available":true,"_id":"67017f734a3e0cf852562032"}],"_id":"67017f734a3e0cf85256202f"},"__v":0},{"_id":"67017fb94a3e0cf85256257c","name":"OXVA XLIM Pro","category":"Devices","image":"http://localhost:5002/uploads/1728151481561.jpg","price":950,"branches":{"main":[{"name":"Brown Wood","available":false,"_id":"67017fb94a3e0cf85256257e"},{"name":"Aurora Pink","available":false,"_id":"67017fb94a3e0cf85256257f"}],"second":[{"name":"Brown Wood","available":false,"_id":"67017fb94a3e0cf852562580"},{"name":"Aurora Pink","available":false,"_id":"67017fb94a3e0cf852562581"}],"third":[{"name":"Brown Wood","available":false,"_id":"67017fb94a3e0cf852562582"},{"name":"Aurora Pink","available":false,"_id":"67017fb94a3e0cf852562583"}],"_id":"67017fb94a3e0cf85256257d"},"__v":0},{"_id":"670180504a3e0cf852563041","name":"OXVA XLIM Cartridge","category":"Pods","image":"http://localhost:5002/uploads/1728151632814.jpg","price":150,"branches":{"main":[{"name":"0.4 ohms","available":true,"_id":"670180504a3e0cf852563043"},{"name":"0.6 ohms","available":true,"_id":"670180504a3e0cf852563044"},{"name":"0.8 ohms","available":true,"_id":"670180504a3e0cf852563045"}],"second":[{"name":"0.4 ohms","available":true,"_id":"670180504a3e0cf852563046"},{"name":"0.6 ohms","available":true,"_id":"670180504a3e0cf852563047"},{"name":"0.8 ohms","available":true,"_id":"670180504a3e0cf852563048"}],"third":[{"name":"0.4 ohms","available":true,"_id":"670180504a3e0cf852563049"},{"name":"0.6 ohms","available":true,"_id":"670180504a3e0cf85256304a"},{"name":"0.8 ohms","available":true,"_id":"670180504a3e0cf85256304b"}],"_id":"670180504a3e0cf852563042"},"__v":0},{"_id":"670180b04a3e0cf8525635b3","name":"Vabeen Indigo","category":"Disposables","image":"http://localhost:5002/uploads/1728151728003.jpg","price":350,"branches":{"main":[{"name":"Juicy Fresh - Bubblegum","available":false,"_id":"670180b04a3e0cf8525635b5"},{"name":"Dark Sparkle - Rich Tobacco","available":true,"_id":"670180b04a3e0cf8525635b6"},{"name":"Fresh Red - Ice Watermelon","available":false,"_id":"670180b04a3e0cf8525635b7"},{"name":"Refreshing Red - Watermelon Strawberry","available":false,"_id":"670180b04a3e0cf8525635b8"},{"name":"Born Purple - Grape Ice","available":true,"_id":"670180b04a3e0cf8525635b9"},{"name":"Ice And Fire - Blueberry Ice","available":false,"_id":"670180b04a3e0cf8525635ba"},{"name":"Amethyst - Purple Potato Custard","available":true,"_id":"670180b04a3e0cf8525635bb"},{"name":"Green Day - Double Apple","available":false,"_id":"670180b04a3e0cf8525635bc"},{"name":"Frozen Pink - Strawberry Ice Cream","available":false,"_id":"670180b04a3e0cf8525635bd"},{"name":"Fresh Pink Sapphire - Strawberry Bubblegum","available":true,"_id":"670180b04a3e0cf8525635be"},{"name":"Funky Trio - Mixed Berries","available":false,"_id":"670180b04a3e0cf8525635bf"},{"name":"Ice Blossom - Ice Lychee","available":true,"_id":"670180b04a3e0cf8525635c0"}],"second":[{"name":"Juicy Fresh - Bubblegum","available":true,"_id":"670180b04a3e0cf8525635c1"},{"name":"Dark Sparkle - Rich Tobacco","available":true,"_id":"670180b04a3e0cf8525635c2"},{"name":"Fresh Red - Ice Watermelon","available":false,"_id":"670180b04a3e0cf8525635c3"},{"name":"Refreshing Red - Watermelon Strawberry","available":true,"_id":"670180b04a3e0cf8525635c4"},{"name":"Born Purple - Grape Ice","available":true,"_id":"670180b04a3e0cf8525635c5"},{"name":"Ice And Fire - Blueberry Ice","available":true,"_id":"670180b04a3e0cf8525635c6"},{"name":"Amethyst - Purple Potato Custard","available":true,"_id":"670180b04a3e0cf8525635c7"},{"name":"Green Day - Double Apple","available":true,"_id":"670180b04a3e0cf8525635c8"},{"name":"Frozen Pink - Strawberry Ice Cream","available":true,"_id":"670180b04a3e0cf8525635c9"},{"name":"Fresh Pink Sapphire - Strawberry Bubblegum","available":true,"_id":"670180b04a3e0cf8525635ca"},{"name":"Funky Trio - Mixed Berries","available":true,"_id":"670180b04a3e0cf8525635cb"},{"name":"Ice Blossom - Ice Lychee","available":true,"_id":"670180b04a3e0cf8525635cc"}],"third":[{"name":"Juicy Fresh - Bubblegum","available":true,"_id":"670180b04a3e0cf8525635cd"},{"name":"Dark Sparkle - Rich Tobacco","available":true,"_id":"670180b04a3e0cf8525635ce"},{"name":"Fresh Red - Ice Watermelon","available":false,"_id":"670180b04a3e0cf8525635cf"},{"name":"Refreshing Red - Watermelon Strawberry","available":true,"_id":"670180b04a3e0cf8525635d0"},{"name":"Born Purple - Grape Ice","available":true,"_id":"670180b04a3e0cf8525635d1"},{"name":"Ice And Fire - Blueberry Ice","available":true,"_id":"670180b04a3e0cf8525635d2"},{"name":"Amethyst - Purple Potato Custard","available":true,"_id":"670180b04a3e0cf8525635d3"},{"name":"Green Day - Double Apple","available":true,"_id":"670180b04a3e0cf8525635d4"},{"name":"Frozen Pink - Strawberry Ice Cream","available":true,"_id":"670180b04a3e0cf8525635d5"},{"name":"Fresh Pink Sapphire - Strawberry Bubblegum","available":true,"_id":"670180b04a3e0cf8525635d6"},{"name":"Funky Trio - Mixed Berries","available":true,"_id":"670180b04a3e0cf8525635d7"},{"name":"Ice Blossom - Ice Lychee","available":true,"_id":"670180b04a3e0cf8525635d8"}],"_id":"670180b04a3e0cf8525635b4"},"__v":0},{"_id":"6701810a4a3e0cf852563b88","name":"XBLACK Elite (8000 Puffs)","category":"Pods","image":"http://localhost:5002/uploads/1728151818930.jpg","price":300,"branches":{"main":[{"name":"Yakult","available":false,"_id":"6701810a4a3e0cf852563b8a"},{"name":"Watermelon","available":false,"_id":"6701810a4a3e0cf852563b8b"},{"name":"Strawberry","available":false,"_id":"6701810a4a3e0cf852563b8c"},{"name":"Blueberry","available":false,"_id":"6701810a4a3e0cf852563b8d"},{"name":"Grapes","available":false,"_id":"6701810a4a3e0cf852563b8e"},{"name":"Blackcurrant","available":false,"_id":"6701810a4a3e0cf852563b8f"},{"name":"Peach","available":false,"_id":"6701810a4a3e0cf852563b90"},{"name":"Bazooka","available":false,"_id":"6701810a4a3e0cf852563b91"},{"name":"Mixed Berries","available":false,"_id":"6701810a4a3e0cf852563b92"},{"name":"Lychee","available":false,"_id":"6701810a4a3e0cf852563b93"},{"name":"Mint","available":false,"_id":"6701810a4a3e0cf852563b94"}],"second":[{"name":"Yakult","available":false,"_id":"6701810a4a3e0cf852563b95"},{"name":"Watermelon","available":false,"_id":"6701810a4a3e0cf852563b96"},{"name":"Strawberry","available":false,"_id":"6701810a4a3e0cf852563b97"},{"name":"Blueberry","available":false,"_id":"6701810a4a3e0cf852563b98"},{"name":"Grapes","available":false,"_id":"6701810a4a3e0cf852563b99"},{"name":"Blackcurrant","available":false,"_id":"6701810a4a3e0cf852563b9a"},{"name":"Peach","available":false,"_id":"6701810a4a3e0cf852563b9b"},{"name":"Bazooka","available":false,"_id":"6701810a4a3e0cf852563b9c"},{"name":"Mixed Berries","available":false,"_id":"6701810a4a3e0cf852563b9d"},{"name":"Lychee","available":false,"_id":"6701810a4a3e0cf852563b9e"},{"name":"Mint","available":false,"_id":"6701810a4a3e0cf852563b9f"}],"third":[{"name":"Yakult","available":false,"_id":"6701810a4a3e0cf852563ba0"},{"name":"Watermelon","available":false,"_id":"6701810a4a3e0cf852563ba1"},{"name":"Strawberry","available":false,"_id":"6701810a4a3e0cf852563ba2"},{"name":"Blueberry","available":false,"_id":"6701810a4a3e0cf852563ba3"},{"name":"Grapes","available":false,"_id":"6701810a4a3e0cf852563ba4"},{"name":"Blackcurrant","available":false,"_id":"6701810a4a3e0cf852563ba5"},{"name":"Peach","available":false,"_id":"6701810a4a3e0cf852563ba6"},{"name":"Bazooka","available":false,"_id":"6701810a4a3e0cf852563ba7"},{"name":"Mixed Berries","available":false,"_id":"6701810a4a3e0cf852563ba8"},{"name":"Lychee","available":false,"_id":"6701810a4a3e0cf852563ba9"},{"name":"Mint","available":false,"_id":"6701810a4a3e0cf852563baa"}],"_id":"6701810a4a3e0cf852563b89"},"__v":0}]